{
  "type": "Feature",
  "stac_version": "1.0.0",
  "id": "830305-8303050000-\u4e09\u982d\u6ca2-gb03_1300667-gb03_1300685",
  "properties": {
    "datetime": "2023-03-09T08:01:14.092125Z"
  },
  "geometry": {
    "type": "MultiLineString",
    "coordinates": [
      [
        [
          139.03301389,
          35.73540306
        ],
        [
          139.03318639,
          35.73539722
        ],
        [
          139.03338667,
          35.73526778
        ],
        [
          139.03346944,
          35.73525083
        ],
        [
          139.03374556,
          35.73526222
        ],
        [
          139.03413222,
          35.73525639
        ],
        [
          139.03449806,
          35.73522861
        ],
        [
          139.03458806,
          35.73520611
        ],
        [
          139.03465694,
          35.73514972
        ],
        [
          139.03494667,
          35.73469917
        ],
        [
          139.03514694,
          35.73454139
        ],
        [
          139.03549194,
          35.73438917
        ],
        [
          139.03567167,
          35.73433861
        ],
        [
          139.03580972,
          35.73431583
        ],
        [
          139.03614111,
          35.73429917
        ],
        [
          139.03619611,
          35.73428778
        ],
        [
          139.03657583,
          35.73425389
        ],
        [
          139.03678306,
          35.73419778
        ],
        [
          139.03690028,
          35.73411917
        ],
        [
          139.03696917,
          35.73404028
        ],
        [
          139.03703139,
          35.73400083
        ],
        [
          139.03714861,
          35.73397833
        ],
        [
          139.03728667,
          35.73393306
        ],
        [
          139.03765944,
          35.73387111
        ],
        [
          139.03780444,
          35.73386556
        ],
        [
          139.03802556,
          35.73383167
        ],
        [
          139.03840528,
          35.73384306
        ],
        [
          139.038495,
          35.73380361
        ],
        [
          139.03855694,
          35.73373583
        ],
        [
          139.03859861,
          35.73364028
        ],
        [
          139.03862611,
          35.73352194
        ],
        [
          139.03867444,
          35.73343167
        ],
        [
          139.03877806,
          35.73329083
        ],
        [
          139.03891611,
          35.73317833
        ],
        [
          139.03910917,
          35.73305417
        ],
        [
          139.03927472,
          35.73297556
        ],
        [
          139.03937139,
          35.73291917
        ],
        [
          139.0395025,
          35.73285167
        ],
        [
          139.03970972,
          35.73269972
        ],
        [
          139.0398,
          35.73264139
        ],
        [
          139.04001361,
          35.7325475
        ],
        [
          139.04017917,
          35.73240667
        ],
        [
          139.040255,
          35.73231667
        ],
        [
          139.04038639,
          35.73213056
        ],
        [
          139.04052444,
          35.73195028
        ],
        [
          139.04067611,
          35.73173056
        ],
        [
          139.04093167,
          35.73143778
        ],
        [
          139.04097306,
          35.73136444
        ],
        [
          139.04104222,
          35.73111083
        ],
        [
          139.041125,
          35.73095333
        ],
        [
          139.04119389,
          35.7308575
        ],
        [
          139.04127528,
          35.73069139
        ],
        [
          139.04127694,
          35.73068833
        ],
        [
          139.04128389,
          35.73050806
        ],
        [
          139.04122861,
          35.73027167
        ],
        [
          139.04119389,
          35.73008
        ],
        [
          139.04118722,
          35.72978694
        ],
        [
          139.04128389,
          35.72968
        ],
        [
          139.04152528,
          35.729635
        ],
        [
          139.0415875,
          35.729635
        ],
        [
          139.04174639,
          35.72960111
        ],
        [
          139.04178083,
          35.72956167
        ],
        [
          139.04179472,
          35.72947167
        ],
        [
          139.04181528,
          35.72941528
        ],
        [
          139.04195306,
          35.72925194
        ],
        [
          139.04205667,
          35.72902639
        ],
        [
          139.04221556,
          35.72874472
        ],
        [
          139.04230528,
          35.72866583
        ],
        [
          139.04241583,
          35.72862083
        ],
        [
          139.04259528,
          35.72853111
        ],
        [
          139.04262972,
          35.72849167
        ],
        [
          139.04265722,
          35.72826056
        ],
        [
          139.04269194,
          35.72814222
        ],
        [
          139.04276083,
          35.72806917
        ],
        [
          139.04287139,
          35.72799028
        ],
        [
          139.04298194,
          35.72788889
        ],
        [
          139.04300944,
          35.72781556
        ],
        [
          139.04300639,
          35.72772972
        ],
        [
          139.04295611,
          35.72763917
        ],
        [
          139.04277889,
          35.72736167
        ]
      ]
    ]
  },
  "links": [
    {
      "rel": "root",
      "href": "../../../catalog.json",
      "type": "application/json"
    },
    {
      "rel": "collection",
      "href": "../collection.json",
      "type": "application/json"
    },
    {
      "rel": "parent",
      "href": "../collection.json",
      "type": "application/json"
    }
  ],
  "assets": {},
  "bbox": [
    139.03301389,
    35.72736167,
    139.04300944,
    35.73540306
  ],
  "stac_extensions": [],
  "collection": "8303050000-\u4e09\u982d\u6ca2"
}