{
  "type": "Feature",
  "stac_version": "1.0.0",
  "id": "830305-8303050022-\u5175\u885b\u5ddd-gb03_1301176-gb03_1301152",
  "properties": {
    "datetime": "2023-03-09T08:01:14.092125Z"
  },
  "geometry": {
    "type": "MultiLineString",
    "coordinates": [
      [
        [
          139.33884,
          35.63746861
        ],
        [
          139.33906778,
          35.63756444
        ],
        [
          139.33907472,
          35.63757583
        ],
        [
          139.3392125,
          35.63763778
        ],
        [
          139.3395575,
          35.63777861
        ],
        [
          139.33990917,
          35.63794194
        ],
        [
          139.34006111,
          35.63806583
        ],
        [
          139.3403025,
          35.638325
        ],
        [
          139.34044722,
          35.63844917
        ],
        [
          139.3406125,
          35.63853917
        ],
        [
          139.34107472,
          35.63873639
        ],
        [
          139.34173694,
          35.63899556
        ],
        [
          139.34188167,
          35.63906889
        ],
        [
          139.34218528,
          35.63919833
        ],
        [
          139.34236444,
          35.63929972
        ],
        [
          139.34244722,
          35.63936167
        ],
        [
          139.34258528,
          35.63951389
        ],
        [
          139.34266806,
          35.63966611
        ],
        [
          139.34271639,
          35.63978417
        ],
        [
          139.34273694,
          35.63994778
        ],
        [
          139.34277139,
          35.6403925
        ],
        [
          139.34279194,
          35.64067972
        ],
        [
          139.34283333,
          35.64096167
        ],
        [
          139.3429575,
          35.64127139
        ],
        [
          139.34310917,
          35.64162639
        ],
        [
          139.34334361,
          35.64217861
        ]
      ]
    ]
  },
  "links": [
    {
      "rel": "root",
      "href": "../../../catalog.json",
      "type": "application/json"
    },
    {
      "rel": "collection",
      "href": "../collection.json",
      "type": "application/json"
    },
    {
      "rel": "parent",
      "href": "../collection.json",
      "type": "application/json"
    }
  ],
  "assets": {},
  "bbox": [
    139.33884,
    35.63746861,
    139.34334361,
    35.64217861
  ],
  "stac_extensions": [],
  "collection": "8303050022-\u5175\u885b\u5ddd"
}