{
  "type": "Feature",
  "stac_version": "1.0.0",
  "id": "830305-8303050000-\u540d\u79f0\u4e0d\u660e-gb03_1301116-gb03_1301108",
  "properties": {
    "datetime": "2023-03-09T08:01:14.092125Z"
  },
  "geometry": {
    "type": "MultiLineString",
    "coordinates": [
      [
        [
          139.24772972,
          35.64909417
        ],
        [
          139.24785389,
          35.64909417
        ],
        [
          139.24793667,
          35.64908278
        ],
        [
          139.24826722,
          35.64893667
        ],
        [
          139.24832944,
          35.64891972
        ],
        [
          139.24875028,
          35.64875639
        ],
        [
          139.24895722,
          35.64872806
        ],
        [
          139.24912278,
          35.6486775
        ],
        [
          139.24928833,
          35.64862667
        ],
        [
          139.24944,
          35.64860417
        ],
        [
          139.24959861,
          35.64859861
        ],
        [
          139.24986083,
          35.64863222
        ],
        [
          139.25001944,
          35.6487
        ],
        [
          139.25010917,
          35.64872806
        ],
        [
          139.250385,
          35.64875056
        ],
        [
          139.25066083,
          35.64875056
        ],
        [
          139.25079194,
          35.64873389
        ],
        [
          139.2512125,
          35.64873389
        ],
        [
          139.2514675,
          35.64876194
        ],
        [
          139.251585,
          35.64879583
        ],
        [
          139.25163306,
          35.64882389
        ],
        [
          139.25176417,
          35.64901556
        ],
        [
          139.25183306,
          35.6493025
        ],
        [
          139.25185389,
          35.64935889
        ],
        [
          139.25190222,
          35.64940944
        ],
        [
          139.25210917,
          35.64949972
        ],
        [
          139.25224694,
          35.64953917
        ],
        [
          139.25230917,
          35.64957861
        ],
        [
          139.25239861,
          35.64975333
        ],
        [
          139.25243306,
          35.64979278
        ],
        [
          139.25259167,
          35.64991667
        ],
        [
          139.25266056,
          35.64998417
        ],
        [
          139.25276417,
          35.650125
        ],
        [
          139.25283306,
          35.65017583
        ],
        [
          139.25292278,
          35.65021528
        ],
        [
          139.25328139,
          35.65028278
        ],
        [
          139.25341944,
          35.65032222
        ],
        [
          139.2536125,
          35.65042361
        ],
        [
          139.25380556,
          35.65050833
        ],
        [
          139.25396417,
          35.65054778
        ],
        [
          139.25414361,
          35.65057583
        ],
        [
          139.254295,
          35.65059833
        ],
        [
          139.25445389,
          35.65060389
        ],
        [
          139.25459861,
          35.65058139
        ],
        [
          139.25489528,
          35.65058722
        ],
        [
          139.25513667,
          35.65062083
        ],
        [
          139.25565389,
          35.65063778
        ],
        [
          139.25599194,
          35.65064917
        ]
      ]
    ]
  },
  "links": [
    {
      "rel": "root",
      "href": "../../../catalog.json",
      "type": "application/json"
    },
    {
      "rel": "collection",
      "href": "../collection.json",
      "type": "application/json"
    },
    {
      "rel": "parent",
      "href": "../collection.json",
      "type": "application/json"
    }
  ],
  "assets": {},
  "bbox": [
    139.24772972,
    35.64859861,
    139.25599194,
    35.65064917
  ],
  "stac_extensions": [],
  "collection": "8303050000-\u540d\u79f0\u4e0d\u660e"
}