{
  "type": "Feature",
  "stac_version": "1.0.0",
  "id": "130000-1300000000-\u540d\u79f0\u4e0d\u660e-gb03_1301482-gb03_1301484",
  "properties": {
    "datetime": "2023-03-09T06:05:21.844086Z"
  },
  "geometry": {
    "type": "MultiLineString",
    "coordinates": [
      [
        [
          142.19011556,
          27.05580694
        ],
        [
          142.19037,
          27.05599694
        ],
        [
          142.19058083,
          27.056075
        ],
        [
          142.1906725,
          27.05608389
        ],
        [
          142.19073778,
          27.05608333
        ],
        [
          142.19095833,
          27.05603806
        ],
        [
          142.19108445,
          27.05604944
        ],
        [
          142.19114722,
          27.05606639
        ],
        [
          142.19133,
          27.05615083
        ],
        [
          142.1914875,
          27.05618472
        ],
        [
          142.19196,
          27.05618472
        ],
        [
          142.19211111,
          27.05617361
        ],
        [
          142.19246389,
          27.05616778
        ],
        [
          142.19258361,
          27.05614528
        ],
        [
          142.19268945,
          27.05613194
        ],
        [
          142.19277889,
          27.05614528
        ],
        [
          142.19288611,
          27.05619611
        ],
        [
          142.19314445,
          27.05638778
        ],
        [
          142.19322,
          27.05642167
        ],
        [
          142.19332722,
          27.05643306
        ],
        [
          142.19350278,
          27.05645083
        ],
        [
          142.19375139,
          27.05650083
        ],
        [
          142.19385639,
          27.05648944
        ],
        [
          142.19396111,
          27.05646083
        ],
        [
          142.19404556,
          27.05641056
        ],
        [
          142.19410222,
          27.05632028
        ],
        [
          142.19410222,
          27.05621306
        ],
        [
          142.19400778,
          27.05597639
        ],
        [
          142.19400778,
          27.05584639
        ],
        [
          142.19403917,
          27.05580694
        ],
        [
          142.19406667,
          27.05579306
        ],
        [
          142.19408333,
          27.05578444
        ],
        [
          142.19421556,
          27.055745
        ],
        [
          142.1942975,
          27.05573361
        ],
        [
          142.19436695,
          27.05570556
        ],
        [
          142.19447389,
          27.05560944
        ],
        [
          142.1946125,
          27.05531056
        ],
        [
          142.19483945,
          27.05492111
        ],
        [
          142.194915,
          27.05484778
        ],
        [
          142.19500333,
          27.05481389
        ],
        [
          142.19525528,
          27.05480833
        ],
        [
          142.19534972,
          27.05481944
        ],
        [
          142.19556417,
          27.05480833
        ],
        [
          142.19562083,
          27.05479139
        ],
        [
          142.19570889,
          27.05474611
        ],
        [
          142.19580972,
          27.05464472
        ],
        [
          142.1958225,
          27.05459056
        ],
        [
          142.19580972,
          27.05452611
        ],
        [
          142.19574695,
          27.05441333
        ],
        [
          142.19574056,
          27.05428361
        ],
        [
          142.19575306,
          27.05417056
        ],
        [
          142.19579722,
          27.05400694
        ],
        [
          142.1958475,
          27.05390556
        ],
        [
          142.19591695,
          27.05383778
        ],
        [
          142.19606195,
          27.05377
        ],
        [
          142.19618778,
          27.05374194
        ],
        [
          142.19631389,
          27.05370278
        ],
        [
          142.19655333,
          27.05359556
        ],
        [
          142.19672972,
          27.05349389
        ],
        [
          142.196805,
          27.05346556
        ],
        [
          142.19703833,
          27.05340361
        ],
        [
          142.19722111,
          27.05338111
        ],
        [
          142.19764306,
          27.05331333
        ],
        [
          142.19776917,
          27.05327389
        ],
        [
          142.19786361,
          27.05320056
        ],
        [
          142.19800222,
          27.05305389
        ],
        [
          142.19806528,
          27.05291278
        ],
        [
          142.19815972,
          27.05275472
        ],
        [
          142.19823556,
          27.05269833
        ],
        [
          142.19836778,
          27.05263056
        ],
        [
          142.19857583,
          27.05257972
        ],
        [
          142.19897278,
          27.05254028
        ],
        [
          142.19922361,
          27.05253417
        ],
        [
          142.19944528,
          27.05254583
        ],
        [
          142.19981695,
          27.05254583
        ],
        [
          142.20030861,
          27.05250639
        ],
        [
          142.20040917,
          27.05248389
        ],
        [
          142.20056056,
          27.05246139
        ],
        [
          142.20089445,
          27.05238806
        ],
        [
          142.20115917,
          27.05233722
        ],
        [
          142.20130389,
          27.05229194
        ],
        [
          142.2014675,
          27.05221861
        ],
        [
          142.20202833,
          27.0518575
        ],
        [
          142.20224889,
          27.05168306
        ],
        [
          142.2023875,
          27.0515475
        ],
        [
          142.20245695,
          27.05149111
        ]
      ]
    ]
  },
  "links": [
    {
      "rel": "root",
      "href": "../../../catalog.json",
      "type": "application/json"
    },
    {
      "rel": "collection",
      "href": "../collection.json",
      "type": "application/json"
    },
    {
      "rel": "parent",
      "href": "../collection.json",
      "type": "application/json"
    }
  ],
  "assets": {},
  "bbox": [
    142.19011556,
    27.05149111,
    142.20245695,
    27.05650083
  ],
  "stac_extensions": [],
  "collection": "1300000000-\u540d\u79f0\u4e0d\u660e"
}