{
  "type": "Feature",
  "stac_version": "1.0.0",
  "id": "830305-8303050005-\u91ce\u5ddd-gb03_1300815-gb03_1300982",
  "properties": {
    "datetime": "2023-03-09T08:01:14.092125Z"
  },
  "geometry": {
    "type": "MultiLineString",
    "coordinates": [
      [
        [
          139.47507694,
          35.70087222
        ],
        [
          139.4751575,
          35.70074306
        ],
        [
          139.47528833,
          35.70058667
        ],
        [
          139.47545444,
          35.69994861
        ],
        [
          139.47550278,
          35.69950361
        ],
        [
          139.47546806,
          35.69919944
        ],
        [
          139.47546806,
          35.69899083
        ],
        [
          139.47553722,
          35.69882194
        ],
        [
          139.47560611,
          35.69874306
        ],
        [
          139.47569611,
          35.69863611
        ],
        [
          139.47579944,
          35.69856833
        ],
        [
          139.47584111,
          35.69852333
        ],
        [
          139.47593083,
          35.6983375
        ],
        [
          139.47604806,
          35.69823028
        ],
        [
          139.47612417,
          35.69813444
        ],
        [
          139.47619306,
          35.6980725
        ],
        [
          139.47636583,
          35.69789778
        ],
        [
          139.47642778,
          35.69774
        ],
        [
          139.47644167,
          35.6977175
        ],
        [
          139.47644167,
          35.69770056
        ],
        [
          139.4764625,
          35.69767806
        ],
        [
          139.47662111,
          35.69741361
        ],
        [
          139.47689,
          35.69703083
        ],
        [
          139.47704222,
          35.69695722
        ],
        [
          139.47744944,
          35.69672056
        ],
        [
          139.4775325,
          35.6966925
        ],
        [
          139.47781556,
          35.69654583
        ],
        [
          139.47817444,
          35.69641056
        ],
        [
          139.47829194,
          35.6963825
        ],
        [
          139.47851306,
          35.69636
        ],
        [
          139.47938306,
          35.6963375
        ],
        [
          139.47990083,
          35.69630917
        ],
        [
          139.48088111,
          35.69628111
        ],
        [
          139.48116417,
          35.69630361
        ],
        [
          139.48155778,
          35.69648389
        ],
        [
          139.48187528,
          35.69666972
        ],
        [
          139.48204806,
          35.6967375
        ],
        [
          139.48253139,
          35.69686694
        ],
        [
          139.48269694,
          35.69690083
        ],
        [
          139.482835,
          35.69691222
        ],
        [
          139.48324944,
          35.69690083
        ],
        [
          139.48331167,
          35.69688972
        ],
        [
          139.48355028,
          35.69688556
        ],
        [
          139.48364278,
          35.69688389
        ],
        [
          139.48391889,
          35.69691778
        ],
        [
          139.48452667,
          35.69697417
        ],
        [
          139.48519639,
          35.69699667
        ],
        [
          139.48547944,
          35.69697972
        ],
        [
          139.48574861,
          35.69697972
        ],
        [
          139.48599028,
          35.69701917
        ],
        [
          139.48623194,
          35.69705306
        ],
        [
          139.4863425,
          35.69708111
        ],
        [
          139.48652222,
          35.69708111
        ],
        [
          139.48664611,
          35.69704194
        ],
        [
          139.48671528,
          35.69698556
        ],
        [
          139.48674278,
          35.69687306
        ],
        [
          139.48681722,
          35.69676917
        ],
        [
          139.48697306,
          35.69677333
        ],
        [
          139.48757833,
          35.69699694
        ],
        [
          139.48777167,
          35.69713222
        ],
        [
          139.48793722,
          35.69728417
        ],
        [
          139.48822,
          35.697425
        ],
        [
          139.48844556,
          35.69749833
        ],
        [
          139.48855889,
          35.69764472
        ],
        [
          139.48855194,
          35.69765028
        ],
        [
          139.48856556,
          35.69766139
        ],
        [
          139.48859333,
          35.69773472
        ],
        [
          139.48904222,
          35.69779111
        ],
        [
          139.48921472,
          35.69785861
        ],
        [
          139.48942194,
          35.69790389
        ],
        [
          139.48964944,
          35.69793194
        ],
        [
          139.48971167,
          35.69793194
        ],
        [
          139.48976,
          35.69788139
        ],
        [
          139.48980139,
          35.69775194
        ],
        [
          139.48986361,
          35.69769556
        ],
        [
          139.49014667,
          35.69767306
        ],
        [
          139.49029167,
          35.69763917
        ],
        [
          139.49056083,
          35.69748139
        ],
        [
          139.49074722,
          35.69736306
        ],
        [
          139.49081639,
          35.69732361
        ],
        [
          139.49089917,
          35.69732944
        ],
        [
          139.49105806,
          35.69736306
        ],
        [
          139.49105889,
          35.69736333
        ],
        [
          139.49129972,
          35.69747028
        ],
        [
          139.49200722,
          35.69740917
        ],
        [
          139.49216278,
          35.69742528
        ],
        [
          139.49218361,
          35.69745889
        ],
        [
          139.49219056,
          35.69754917
        ],
        [
          139.492225,
          35.69760556
        ],
        [
          139.49231472,
          35.69766167
        ],
        [
          139.49241139,
          35.69769556
        ],
        [
          139.49257722,
          35.69776333
        ],
        [
          139.49270139,
          35.69779139
        ],
        [
          139.492805,
          35.69780833
        ],
        [
          139.49293139,
          35.69786667
        ],
        [
          139.49314222,
          35.69804
        ],
        [
          139.49336528,
          35.69801111
        ],
        [
          139.49347694,
          35.69797389
        ],
        [
          139.49370444,
          35.69773444
        ],
        [
          139.49388639,
          35.69747833
        ],
        [
          139.49417889,
          35.69741389
        ],
        [
          139.49424083,
          35.6974025
        ],
        [
          139.49434444,
          35.69737444
        ],
        [
          139.49454472,
          35.69736306
        ],
        [
          139.49466917,
          35.69730111
        ],
        [
          139.49475194,
          35.69726167
        ],
        [
          139.49482778,
          35.69723917
        ],
        [
          139.49489,
          35.69731806
        ],
        [
          139.49497278,
          35.697335
        ],
        [
          139.49510417,
          35.697335
        ],
        [
          139.49516611,
          35.69731806
        ],
        [
          139.49538028,
          35.69732361
        ],
        [
          139.49541472,
          35.697335
        ],
        [
          139.49555278,
          35.697335
        ],
        [
          139.49572556,
          35.69730694
        ],
        [
          139.49620194,
          35.69730111
        ],
        [
          139.49644361,
          35.69728417
        ],
        [
          139.49654,
          35.69727306
        ],
        [
          139.49660917,
          35.69724472
        ],
        [
          139.49667111,
          35.69720528
        ],
        [
          139.49676778,
          35.69711528
        ],
        [
          139.49678861,
          35.69711167
        ],
        [
          139.496985,
          35.69704583
        ],
        [
          139.49785194,
          35.69658028
        ],
        [
          139.49876333,
          35.6960675
        ],
        [
          139.49901194,
          35.69588722
        ],
        [
          139.49918472,
          35.69574639
        ],
        [
          139.49930889,
          35.69560556
        ],
        [
          139.49948167,
          35.69535194
        ],
        [
          139.49966111,
          35.69503111
        ],
        [
          139.4997025,
          35.69493528
        ],
        [
          139.49976472,
          35.69480556
        ],
        [
          139.49999944,
          35.69428722
        ],
        [
          139.50000806,
          35.69425306
        ],
        [
          139.50003389,
          35.69419722
        ],
        [
          139.50023417,
          35.69379722
        ],
        [
          139.50032389,
          35.69365056
        ],
        [
          139.5004,
          35.69358306
        ],
        [
          139.50046194,
          35.69356056
        ],
        [
          139.50063472,
          35.69353222
        ],
        [
          139.50133889,
          35.69351528
        ],
        [
          139.50146722,
          35.69351056
        ],
        [
          139.50192889,
          35.69362
        ],
        [
          139.50258278,
          35.69373833
        ],
        [
          139.50289389,
          35.69379778
        ],
        [
          139.50370028,
          35.69387028
        ],
        [
          139.50389361,
          35.69388167
        ],
        [
          139.50458389,
          35.69391583
        ],
        [
          139.50513611,
          35.69394389
        ],
        [
          139.50609583,
          35.69397778
        ],
        [
          139.50682083,
          35.69398889
        ],
        [
          139.50704889,
          35.69397778
        ],
        [
          139.50709028,
          35.69397778
        ],
        [
          139.50723528,
          35.69396083
        ],
        [
          139.5077325,
          35.69391
        ],
        [
          139.50803611,
          35.69385944
        ],
        [
          139.50891972,
          35.69340306
        ],
        [
          139.50904417,
          35.69334667
        ],
        [
          139.50915444,
          35.69330722
        ],
        [
          139.50944444,
          35.69323972
        ],
        [
          139.50964833,
          35.69323528
        ],
        [
          139.50985194,
          35.69325083
        ],
        [
          139.51050111,
          35.69341417
        ],
        [
          139.51077722,
          35.69349306
        ],
        [
          139.51095667,
          35.69354944
        ],
        [
          139.51130889,
          35.69360583
        ],
        [
          139.5118125,
          35.69365083
        ],
        [
          139.51220611,
          35.69364528
        ],
        [
          139.51244778,
          35.69362833
        ],
        [
          139.51282778,
          35.69356639
        ],
        [
          139.51344917,
          35.69336944
        ],
        [
          139.51357333,
          35.69333556
        ],
        [
          139.51361833,
          35.69332
        ],
        [
          139.51378556,
          35.69326222
        ],
        [
          139.51425,
          35.69309889
        ],
        [
          139.51440889,
          35.69305389
        ],
        [
          139.51490611,
          35.69287917
        ],
        [
          139.51627306,
          35.69240028
        ],
        [
          139.51653528,
          35.69231028
        ],
        [
          139.51767472,
          35.69190472
        ],
        [
          139.5180475,
          35.69174139
        ],
        [
          139.51840667,
          35.69153278
        ],
        [
          139.5186,
          35.69138639
        ],
        [
          139.51870361,
          35.69129056
        ],
        [
          139.51879333,
          35.69122306
        ],
        [
          139.51911778,
          35.6908625
        ],
        [
          139.51958722,
          35.69029889
        ],
        [
          139.51976,
          35.69013
        ],
        [
          139.52006389,
          35.68989917
        ],
        [
          139.52040194,
          35.68970194
        ],
        [
          139.52062278,
          35.68958361
        ],
        [
          139.52065722,
          35.68955556
        ],
        [
          139.52084361,
          35.68946528
        ],
        [
          139.52136167,
          35.68920056
        ],
        [
          139.52167222,
          35.68903139
        ],
        [
          139.52201056,
          35.6888625
        ],
        [
          139.52214194,
          35.68878917
        ],
        [
          139.52257694,
          35.68856389
        ],
        [
          139.52273389,
          35.68848306
        ],
        [
          139.52294972,
          35.68837222
        ],
        [
          139.52311556,
          35.6882825
        ],
        [
          139.5234725,
          35.68810972
        ],
        [
          139.52352278,
          35.68808528
        ],
        [
          139.52363194,
          35.68801167
        ],
        [
          139.52381972,
          35.68791611
        ],
        [
          139.52443417,
          35.68758361
        ],
        [
          139.52454889,
          35.68750056
        ],
        [
          139.5246825,
          35.68740333
        ],
        [
          139.52475167,
          35.68734139
        ],
        [
          139.52482694,
          35.68725528
        ],
        [
          139.52502778,
          35.68702583
        ],
        [
          139.52520056,
          35.68676667
        ],
        [
          139.52527639,
          35.68659194
        ],
        [
          139.52534667,
          35.686345
        ],
        [
          139.52536611,
          35.68627694
        ],
        [
          139.52542833,
          35.68591056
        ],
        [
          139.52548333,
          35.68563778
        ],
        [
          139.52555278,
          35.68529639
        ],
        [
          139.52557361,
          35.68525694
        ],
        [
          139.52568417,
          35.68484
        ],
        [
          139.52580139,
          35.68464833
        ],
        [
          139.52584278,
          35.68461472
        ],
        [
          139.5258775,
          35.68456389
        ],
        [
          139.52611889,
          35.68436667
        ],
        [
          139.5264225,
          35.68418667
        ],
        [
          139.52701944,
          35.68393472
        ],
        [
          139.52779667,
          35.68360639
        ],
        [
          139.52848722,
          35.68327944
        ],
        [
          139.5289775,
          35.68295833
        ],
        [
          139.52914306,
          35.68276694
        ],
        [
          139.52921222,
          35.68263722
        ],
        [
          139.52932278,
          35.68237278
        ],
        [
          139.52930444,
          35.68203028
        ],
        [
          139.52939861,
          35.68153889
        ],
        [
          139.52943306,
          35.68133028
        ],
        [
          139.52952972,
          35.68103167
        ],
        [
          139.52964028,
          35.68086278
        ],
        [
          139.53000639,
          35.68040639
        ],
        [
          139.53015833,
          35.68015861
        ],
        [
          139.53024806,
          35.67996694
        ],
        [
          139.53032667,
          35.67968222
        ],
        [
          139.53035528,
          35.67934222
        ],
        [
          139.53041361,
          35.67907694
        ],
        [
          139.53043444,
          35.67895861
        ],
        [
          139.53048972,
          35.67851889
        ],
        [
          139.53059333,
          35.67778111
        ],
        [
          139.53065528,
          35.67738667
        ],
        [
          139.53068306,
          35.67711056
        ],
        [
          139.53073833,
          35.67677833
        ],
        [
          139.53077972,
          35.67661472
        ],
        [
          139.530835,
          35.67643444
        ],
        [
          139.53093167,
          35.67624861
        ],
        [
          139.53101806,
          35.67612972
        ],
        [
          139.53119389,
          35.67588806
        ],
        [
          139.53159444,
          35.67540361
        ],
        [
          139.53222278,
          35.67473333
        ],
        [
          139.53225028,
          35.674705
        ],
        [
          139.53273361,
          35.67422611
        ],
        [
          139.53360389,
          35.67331917
        ],
        [
          139.53377639,
          35.67312778
        ],
        [
          139.53403889,
          35.67286278
        ],
        [
          139.53447389,
          35.67241778
        ],
        [
          139.53466694,
          35.67224861
        ],
        [
          139.53495694,
          35.67201778
        ],
        [
          139.53588222,
          35.67138139
        ],
        [
          139.53604778,
          35.67127417
        ],
        [
          139.53622056,
          35.67116722
        ],
        [
          139.53649667,
          35.67096444
        ],
        [
          139.53662778,
          35.67084611
        ],
        [
          139.53686306,
          35.67062167
        ]
      ]
    ]
  },
  "links": [
    {
      "rel": "root",
      "href": "../../../catalog.json",
      "type": "application/json"
    },
    {
      "rel": "collection",
      "href": "../collection.json",
      "type": "application/json"
    },
    {
      "rel": "parent",
      "href": "../collection.json",
      "type": "application/json"
    }
  ],
  "assets": {},
  "bbox": [
    139.47507694,
    35.67062167,
    139.53686306,
    35.70087222
  ],
  "stac_extensions": [],
  "collection": "8303050005-\u91ce\u5ddd"
}