{
  "type": "Feature",
  "stac_version": "1.0.0",
  "id": "830305-8303050000-\u540d\u79f0\u4e0d\u660e-gb03_1301211-gb03_1301245",
  "properties": {
    "datetime": "2023-03-09T06:08:01.155220Z"
  },
  "geometry": {
    "type": "MultiLineString",
    "coordinates": [
      [
        [
          139.58032,
          35.63062778
        ],
        [
          139.58036139,
          35.63058278
        ],
        [
          139.58073389,
          35.63018306
        ],
        [
          139.58090639,
          35.63007028
        ],
        [
          139.581065,
          35.62999139
        ],
        [
          139.58121,
          35.62994639
        ],
        [
          139.58133417,
          35.62991833
        ],
        [
          139.58140306,
          35.6299125
        ],
        [
          139.58150194,
          35.62989944
        ],
        [
          139.58175833,
          35.62985528
        ],
        [
          139.58187972,
          35.62983361
        ],
        [
          139.5821475,
          35.62968111
        ],
        [
          139.58225333,
          35.6295225
        ],
        [
          139.58238583,
          35.62925444
        ],
        [
          139.58247417,
          35.62901556
        ],
        [
          139.58250111,
          35.62894889
        ],
        [
          139.58255139,
          35.62889583
        ],
        [
          139.58259167,
          35.62886444
        ],
        [
          139.58265694,
          35.62882389
        ],
        [
          139.58283778,
          35.62875778
        ],
        [
          139.58293667,
          35.62874806
        ],
        [
          139.58305361,
          35.62874944
        ],
        [
          139.58331083,
          35.62881222
        ],
        [
          139.58345333,
          35.62887556
        ],
        [
          139.58385611,
          35.62911222
        ],
        [
          139.58410139,
          35.62932556
        ],
        [
          139.58415361,
          35.62935528
        ],
        [
          139.58419611,
          35.629365
        ],
        [
          139.58437111,
          35.62935889
        ],
        [
          139.58449417,
          35.62931611
        ],
        [
          139.5845975,
          35.62927583
        ],
        [
          139.58497472,
          35.62910972
        ],
        [
          139.58504972,
          35.62911111
        ],
        [
          139.58524778,
          35.62908889
        ],
        [
          139.585495,
          35.62907722
        ],
        [
          139.5859325,
          35.62903222
        ],
        [
          139.58635167,
          35.62894667
        ],
        [
          139.58651417,
          35.62893111
        ],
        [
          139.58657028,
          35.6289375
        ],
        [
          139.58660111,
          35.62895361
        ],
        [
          139.58662639,
          35.62898111
        ],
        [
          139.58664917,
          35.62901083
        ],
        [
          139.58666389,
          35.62904667
        ],
        [
          139.58666417,
          35.62909972
        ],
        [
          139.58660139,
          35.62921833
        ],
        [
          139.58660139,
          35.62927139
        ],
        [
          139.58660722,
          35.62930972
        ],
        [
          139.58662583,
          35.62934167
        ],
        [
          139.58667639,
          35.62938361
        ],
        [
          139.58684806,
          35.62947111
        ],
        [
          139.58692639,
          35.62950528
        ],
        [
          139.58698556,
          35.62950528
        ],
        [
          139.58701694,
          35.62948028
        ],
        [
          139.58704722,
          35.62944306
        ],
        [
          139.58721111,
          35.62931861
        ],
        [
          139.5873325,
          35.62921528
        ],
        [
          139.58751778,
          35.62904861
        ],
        [
          139.58763528,
          35.62893278
        ],
        [
          139.58775111,
          35.6288875
        ],
        [
          139.587845,
          35.62887806
        ],
        [
          139.58793694,
          35.62886722
        ],
        [
          139.58798028,
          35.62888444
        ],
        [
          139.58803861,
          35.62889889
        ],
        [
          139.58808861,
          35.62890306
        ],
        [
          139.58814167,
          35.6288875
        ],
        [
          139.58833833,
          35.62878694
        ],
        [
          139.58841333,
          35.62877361
        ],
        [
          139.58849111,
          35.62876528
        ],
        [
          139.58861111,
          35.62875917
        ],
        [
          139.58866278,
          35.628745
        ],
        [
          139.58872278,
          35.62870556
        ],
        [
          139.58879139,
          35.62865556
        ],
        [
          139.58885194,
          35.62861222
        ],
        [
          139.58889472,
          35.62859639
        ],
        [
          139.58896972,
          35.62858694
        ],
        [
          139.58906639,
          35.62859639
        ],
        [
          139.5891475,
          35.62861167
        ],
        [
          139.58930778,
          35.628685
        ],
        [
          139.58937972,
          35.62868278
        ],
        [
          139.58947472,
          35.62867972
        ],
        [
          139.58954694,
          35.62864667
        ],
        [
          139.58958667,
          35.62860167
        ],
        [
          139.58961889,
          35.62856361
        ],
        [
          139.58980444,
          35.62840889
        ],
        [
          139.58987333,
          35.628355
        ],
        [
          139.58991,
          35.62832528
        ],
        [
          139.58991444,
          35.62830194
        ],
        [
          139.58988194,
          35.62824056
        ],
        [
          139.58981333,
          35.62815306
        ],
        [
          139.58980389,
          35.628125
        ],
        [
          139.58983833,
          35.62809361
        ],
        [
          139.58985472,
          35.62807889
        ],
        [
          139.59011944,
          35.62783778
        ],
        [
          139.59020222,
          35.62774861
        ],
        [
          139.59032417,
          35.62765472
        ],
        [
          139.59042722,
          35.62764556
        ],
        [
          139.59051806,
          35.62764556
        ],
        [
          139.59055222,
          35.62762972
        ],
        [
          139.59055861,
          35.62760167
        ],
        [
          139.59052111,
          35.627555
        ],
        [
          139.59045222,
          35.6274925
        ],
        [
          139.59042111,
          35.62746444
        ],
        [
          139.59041806,
          35.6274425
        ],
        [
          139.59042722,
          35.6274175
        ],
        [
          139.59048667,
          35.62738306
        ],
        [
          139.59052722,
          35.62735694
        ],
        [
          139.59073472,
          35.62734778
        ],
        [
          139.59083694,
          35.62732222
        ],
        [
          139.59089278,
          35.62729889
        ],
        [
          139.59097417,
          35.62721778
        ],
        [
          139.59106639,
          35.62710778
        ],
        [
          139.59111667,
          35.62701472
        ],
        [
          139.59115222,
          35.62693972
        ],
        [
          139.59117944,
          35.62676389
        ],
        [
          139.59118111,
          35.62671056
        ],
        [
          139.59117194,
          35.62666806
        ],
        [
          139.59114417,
          35.62658528
        ],
        [
          139.59110028,
          35.62647583
        ],
        [
          139.59110333,
          35.62641028
        ],
        [
          139.59118167,
          35.62637917
        ],
        [
          139.59127833,
          35.62638222
        ],
        [
          139.59150667,
          35.62640722
        ],
        [
          139.59158528,
          35.62640639
        ],
        [
          139.59167222,
          35.62639972
        ],
        [
          139.59179722,
          35.62637583
        ],
        [
          139.59196583,
          35.62634167
        ],
        [
          139.59207222,
          35.62630111
        ],
        [
          139.59215333,
          35.62629167
        ],
        [
          139.592275,
          35.62629778
        ],
        [
          139.59240944,
          35.62636278
        ],
        [
          139.59253444,
          35.62643528
        ],
        [
          139.59270306,
          35.62647889
        ],
        [
          139.59282167,
          35.62648222
        ],
        [
          139.59294056,
          35.62646972
        ],
        [
          139.59305306,
          35.62646972
        ],
        [
          139.59312167,
          35.62647278
        ],
        [
          139.59315917,
          35.62650722
        ],
        [
          139.59322806,
          35.62655694
        ],
        [
          139.59326861,
          35.62656639
        ],
        [
          139.593325,
          35.62654778
        ],
        [
          139.59341556,
          35.62650083
        ],
        [
          139.59348417,
          35.62645083
        ],
        [
          139.59348444,
          35.62645056
        ],
        [
          139.59368389,
          35.62628139
        ],
        [
          139.59380889,
          35.62620028
        ],
        [
          139.59383722,
          35.62618556
        ],
        [
          139.5938775,
          35.62618889
        ],
        [
          139.59393389,
          35.62620333
        ],
        [
          139.59414639,
          35.62621889
        ],
        [
          139.59422639,
          35.62621417
        ],
        [
          139.59432139,
          35.62619389
        ],
        [
          139.59461,
          35.62603528
        ],
        [
          139.59483389,
          35.62594111
        ],
        [
          139.59511694,
          35.62583639
        ],
        [
          139.59535889,
          35.62576639
        ],
        [
          139.59540889,
          35.62571944
        ],
        [
          139.59542444,
          35.62566944
        ],
        [
          139.59542778,
          35.62556639
        ],
        [
          139.59540889,
          35.62530444
        ],
        [
          139.59532306,
          35.62490528
        ],
        [
          139.59529806,
          35.62480222
        ],
        [
          139.595295,
          35.62472417
        ],
        [
          139.59530444,
          35.62455222
        ],
        [
          139.59535444,
          35.6243775
        ],
        [
          139.59542611,
          35.62413389
        ],
        [
          139.59542944,
          35.62401833
        ],
        [
          139.59547583,
          35.62375583
        ],
        [
          139.59547472,
          35.62372333
        ],
        [
          139.59547389,
          35.62368611
        ],
        [
          139.59543778,
          35.62364278
        ],
        [
          139.59537528,
          35.62359167
        ],
        [
          139.59522806,
          35.6234875
        ],
        [
          139.5951975,
          35.62345778
        ],
        [
          139.59518167,
          35.62341056
        ],
        [
          139.59518167,
          35.62337917
        ],
        [
          139.59521111,
          35.62333556
        ],
        [
          139.59526556,
          35.62328944
        ],
        [
          139.59535722,
          35.62323917
        ],
        [
          139.59541889,
          35.62322639
        ],
        [
          139.59547111,
          35.62322472
        ],
        [
          139.59560361,
          35.62322028
        ],
        [
          139.59595028,
          35.623195
        ],
        [
          139.59610222,
          35.62318944
        ],
        [
          139.59640944,
          35.62316056
        ],
        [
          139.59670028,
          35.62313556
        ],
        [
          139.59716472,
          35.62306389
        ],
        [
          139.59762722,
          35.622995
        ],
        [
          139.59780833,
          35.62295139
        ],
        [
          139.59803028,
          35.62288556
        ],
        [
          139.59818028,
          35.62279222
        ],
        [
          139.59824333,
          35.62275028
        ],
        [
          139.59842083,
          35.62257389
        ],
        [
          139.59844583,
          35.62248028
        ],
        [
          139.59846833,
          35.62210333
        ],
        [
          139.59851333,
          35.62191278
        ],
        [
          139.59858222,
          35.62166
        ],
        [
          139.59864056,
          35.62158083
        ],
        [
          139.59890278,
          35.62128222
        ],
        [
          139.59903806,
          35.62117111
        ],
        [
          139.599365,
          35.62095028
        ],
        [
          139.599765,
          35.62070222
        ],
        [
          139.59993056,
          35.62061778
        ],
        [
          139.60008222,
          35.62055583
        ],
        [
          139.60082722,
          35.62040917
        ],
        [
          139.60090306,
          35.62038111
        ],
        [
          139.60096667,
          35.62031778
        ],
        [
          139.60101139,
          35.62025417
        ],
        [
          139.60106389,
          35.62017806
        ],
        [
          139.60139278,
          35.61971056
        ],
        [
          139.60141472,
          35.61968306
        ],
        [
          139.60144306,
          35.61964944
        ],
        [
          139.60149194,
          35.61961639
        ],
        [
          139.60153778,
          35.61959806
        ],
        [
          139.60169556,
          35.61954833
        ],
        [
          139.60193083,
          35.61949111
        ],
        [
          139.60249,
          35.61934139
        ],
        [
          139.60262889,
          35.6193025
        ],
        [
          139.60273028,
          35.61928972
        ],
        [
          139.60280278,
          35.61929083
        ],
        [
          139.60289111,
          35.61931083
        ],
        [
          139.603,
          35.61935028
        ],
        [
          139.6032,
          35.61942361
        ],
        [
          139.60350833,
          35.61955111
        ],
        [
          139.60376889,
          35.61965028
        ],
        [
          139.60423917,
          35.61981417
        ],
        [
          139.60490528,
          35.61987028
        ],
        [
          139.60507333,
          35.6199125
        ],
        [
          139.60518278,
          35.619945
        ],
        [
          139.60542361,
          35.62011444
        ],
        [
          139.60572806,
          35.62034667
        ],
        [
          139.60578944,
          35.6203675
        ],
        [
          139.60590722,
          35.62038583
        ],
        [
          139.60607056,
          35.62039361
        ],
        [
          139.60611361,
          35.62040028
        ],
        [
          139.60612306,
          35.62040222
        ],
        [
          139.60618,
          35.62049278
        ],
        [
          139.60620056,
          35.62050861
        ],
        [
          139.60624139,
          35.62050583
        ],
        [
          139.60644861,
          35.62049389
        ],
        [
          139.60674444,
          35.62048472
        ],
        [
          139.60682111,
          35.62047111
        ],
        [
          139.60688333,
          35.62047694
        ],
        [
          139.60690389,
          35.62049944
        ],
        [
          139.60693806,
          35.62058389
        ],
        [
          139.60698639,
          35.62082611
        ],
        [
          139.60702917,
          35.62103167
        ],
        [
          139.60705111,
          35.6211225
        ],
        [
          139.60708917,
          35.62119861
        ],
        [
          139.60716583,
          35.62133889
        ],
        [
          139.60747611,
          35.62200361
        ],
        [
          139.6075175,
          35.62207111
        ],
        [
          139.60758944,
          35.62207778
        ],
        [
          139.60766944,
          35.62206556
        ],
        [
          139.60773833,
          35.62202611
        ],
        [
          139.60775889,
          35.62199778
        ],
        [
          139.60802111,
          35.62176139
        ],
        [
          139.60810389,
          35.62171083
        ],
        [
          139.60826944,
          35.62162639
        ],
        [
          139.60846472,
          35.62154944
        ],
        [
          139.60852472,
          35.62151917
        ],
        [
          139.608635,
          35.62145167
        ],
        [
          139.60869722,
          35.62138389
        ],
        [
          139.60890278,
          35.62121194
        ],
        [
          139.60907639,
          35.62109667
        ],
        [
          139.60921444,
          35.62098389
        ],
        [
          139.60931806,
          35.62092194
        ],
        [
          139.60942833,
          35.620905
        ],
        [
          139.60953139,
          35.62093333
        ],
        [
          139.60969028,
          35.62104028
        ],
        [
          139.61006944,
          35.62115861
        ],
        [
          139.61038333,
          35.62122417
        ],
        [
          139.61060778,
          35.62127833
        ]
      ]
    ]
  },
  "links": [
    {
      "rel": "root",
      "href": "../../../catalog.json",
      "type": "application/json"
    },
    {
      "rel": "collection",
      "href": "../collection.json",
      "type": "application/json"
    },
    {
      "rel": "parent",
      "href": "../collection.json",
      "type": "application/json"
    }
  ],
  "assets": {},
  "bbox": [
    139.58032,
    35.61928972,
    139.61060778,
    35.63062778
  ],
  "stac_extensions": [],
  "collection": "8303050000-\u540d\u79f0\u4e0d\u660e"
}