{
  "type": "Feature",
  "stac_version": "1.0.0",
  "id": "830303-8303030000-\u9577\u5cf6\u5ddd-gb03_1301076-gb03_1300993",
  "properties": {
    "datetime": "2023-03-09T08:01:14.092125Z"
  },
  "geometry": {
    "type": "MultiLineString",
    "coordinates": [
      [
        [
          139.85780428,
          35.6580397
        ],
        [
          139.85841656,
          35.65815098
        ],
        [
          139.85905965,
          35.65836802
        ],
        [
          139.85983495,
          35.65837536
        ],
        [
          139.86035108,
          35.65843298
        ],
        [
          139.86102947,
          35.6584394
        ],
        [
          139.8613822,
          35.65862731
        ],
        [
          139.86128079,
          35.65894277
        ],
        [
          139.86114596,
          35.65933701
        ],
        [
          139.86114034,
          35.65973248
        ],
        [
          139.86116778,
          35.66007552
        ],
        [
          139.86151715,
          35.66050071
        ],
        [
          139.86176848,
          35.66100408
        ],
        [
          139.86195671,
          35.66140138
        ],
        [
          139.86236808,
          35.66201173
        ],
        [
          139.86284556,
          35.66251723
        ],
        [
          139.86322576,
          35.66304818
        ],
        [
          139.86370064,
          35.66373822
        ],
        [
          139.86408422,
          35.66403189
        ],
        [
          139.8645324,
          35.66432617
        ],
        [
          139.86482018,
          35.66453982
        ],
        [
          139.86517071,
          35.66488591
        ],
        [
          139.8654893,
          35.66520533
        ],
        [
          139.86574552,
          35.66536595
        ],
        [
          139.86600062,
          35.66560566
        ],
        [
          139.86616104,
          35.66568628
        ],
        [
          139.86641913,
          35.66571508
        ],
        [
          139.86677414,
          35.66574478
        ],
        [
          139.86709684,
          35.66577419
        ],
        [
          139.86767726,
          35.66585875
        ],
        [
          139.86780575,
          35.6659127
        ],
        [
          139.86835498,
          35.66591786
        ],
        [
          139.86893577,
          35.66597605
        ],
        [
          139.86945158,
          35.66606
        ],
        [
          139.87000006,
          35.66611789
        ],
        [
          139.87035508,
          35.66614759
        ],
        [
          139.87112898,
          35.66626032
        ],
        [
          139.87141863,
          35.66634214
        ],
        [
          139.87183752,
          35.66642516
        ],
        [
          139.87219179,
          35.66650759
        ],
        [
          139.87241768,
          35.66656966
        ],
        [
          139.87372861,
          35.66706167
        ],
        [
          139.87511083,
          35.66768694
        ],
        [
          139.87664028,
          35.66834028
        ],
        [
          139.87711111,
          35.66852611
        ],
        [
          139.87739389,
          35.66859556
        ],
        [
          139.87756833,
          35.66860306
        ],
        [
          139.87799417,
          35.66858361
        ],
        [
          139.87830056,
          35.66849528
        ],
        [
          139.87879556,
          35.66821833
        ],
        [
          139.87899889,
          35.66816028
        ],
        [
          139.87915917,
          35.66816417
        ],
        [
          139.87989917,
          35.6682375
        ],
        [
          139.88006417,
          35.6682875
        ],
        [
          139.88028111,
          35.66843
        ],
        [
          139.88100889,
          35.668735
        ],
        [
          139.88150389,
          35.66895056
        ],
        [
          139.88209417,
          35.66930111
        ],
        [
          139.88221528,
          35.66935528
        ],
        [
          139.88239611,
          35.66943583
        ],
        [
          139.88269306,
          35.66953583
        ],
        [
          139.88298528,
          35.6695975
        ],
        [
          139.88337667,
          35.66961278
        ],
        [
          139.88379667,
          35.6696225
        ],
        [
          139.88395944,
          35.66963611
        ]
      ]
    ]
  },
  "links": [
    {
      "rel": "root",
      "href": "../../../catalog.json",
      "type": "application/json"
    },
    {
      "rel": "collection",
      "href": "../collection.json",
      "type": "application/json"
    },
    {
      "rel": "parent",
      "href": "../collection.json",
      "type": "application/json"
    }
  ],
  "assets": {},
  "bbox": [
    139.85780428,
    35.6580397,
    139.88395944,
    35.66963611
  ],
  "stac_extensions": [],
  "collection": "8303030000-\u9577\u5cf6\u5ddd"
}