{
  "type": "Feature",
  "stac_version": "1.0.0",
  "id": "830305-8303050000-\u30bb\u30df\u6ca2-gb03_1300133-gb03_1300157",
  "properties": {
    "datetime": "2023-03-09T08:01:14.092125Z"
  },
  "geometry": {
    "type": "MultiLineString",
    "coordinates": [
      [
        [
          139.15034174,
          35.82991515
        ],
        [
          139.15089374,
          35.82976124
        ],
        [
          139.15134701,
          35.82956521
        ],
        [
          139.15185387,
          35.8292076
        ],
        [
          139.1523645,
          35.82868763
        ],
        [
          139.15297479,
          35.8281692
        ],
        [
          139.15363774,
          35.82752977
        ],
        [
          139.15404961,
          35.82696768
        ],
        [
          139.15441351,
          35.82632365
        ],
        [
          139.1548799,
          35.82555938
        ],
        [
          139.15519584,
          35.82483341
        ],
        [
          139.15586156,
          35.8240722
        ],
        [
          139.15638194,
          35.82383444
        ]
      ]
    ]
  },
  "links": [
    {
      "rel": "root",
      "href": "../../../catalog.json",
      "type": "application/json"
    },
    {
      "rel": "collection",
      "href": "../collection.json",
      "type": "application/json"
    },
    {
      "rel": "parent",
      "href": "../collection.json",
      "type": "application/json"
    }
  ],
  "assets": {},
  "bbox": [
    139.15034174,
    35.82383444,
    139.15638194,
    35.82991515
  ],
  "stac_extensions": [],
  "collection": "8303050000-\u30bb\u30df\u6ca2"
}