{
  "type": "Feature",
  "stac_version": "1.0.0",
  "id": "830305-8303050000-\u540d\u79f0\u4e0d\u660e-gb03_1301231-gb03_1301207",
  "properties": {
    "datetime": "2023-03-09T08:01:14.092125Z"
  },
  "geometry": {
    "type": "MultiLineString",
    "coordinates": [
      [
        [
          139.30126556,
          35.62359917
        ],
        [
          139.30133472,
          35.62359917
        ],
        [
          139.30164472,
          35.62362556
        ],
        [
          139.30170222,
          35.62364722
        ],
        [
          139.30192056,
          35.62376806
        ],
        [
          139.30212056,
          35.62390306
        ],
        [
          139.30219667,
          35.62393694
        ],
        [
          139.30230694,
          35.62393111
        ],
        [
          139.30242417,
          35.62388611
        ],
        [
          139.30255528,
          35.62389167
        ],
        [
          139.30293472,
          35.62397056
        ],
        [
          139.30300361,
          35.62400444
        ],
        [
          139.30312083,
          35.62411139
        ],
        [
          139.30316222,
          35.62412833
        ],
        [
          139.30323806,
          35.62412278
        ],
        [
          139.30336222,
          35.62406639
        ],
        [
          139.30341056,
          35.62402694
        ],
        [
          139.3034725,
          35.62402694
        ],
        [
          139.3039275,
          35.62422972
        ],
        [
          139.30398972,
          35.62426361
        ],
        [
          139.30402,
          35.62428194
        ],
        [
          139.30404778,
          35.6243175
        ],
        [
          139.30406556,
          35.62442694
        ],
        [
          139.30407944,
          35.62447194
        ],
        [
          139.30413444,
          35.62455083
        ],
        [
          139.30428639,
          35.62468056
        ],
        [
          139.30430694,
          35.62475361
        ],
        [
          139.30437583,
          35.62491722
        ],
        [
          139.30436222,
          35.62498472
        ],
        [
          139.30434139,
          35.62502417
        ],
        [
          139.30433444,
          35.62510306
        ],
        [
          139.30435528,
          35.62513694
        ],
        [
          139.30440361,
          35.6251875
        ],
        [
          139.30450694,
          35.62523833
        ],
        [
          139.30456917,
          35.62528333
        ],
        [
          139.30461722,
          35.62538472
        ],
        [
          139.30462417,
          35.62549722
        ],
        [
          139.30459667,
          35.62551417
        ],
        [
          139.30459639,
          35.62554306
        ],
        [
          139.30459444,
          35.62559333
        ],
        [
          139.30455194,
          35.6256525
        ],
        [
          139.30452778,
          35.6257225
        ],
        [
          139.30455528,
          35.62581278
        ],
        [
          139.30458972,
          35.62588028
        ],
        [
          139.30460361,
          35.62596472
        ],
        [
          139.30470694,
          35.62606611
        ],
        [
          139.304845,
          35.626145
        ],
        [
          139.30496222,
          35.62615083
        ],
        [
          139.30501556,
          35.6261375
        ],
        [
          139.30505278,
          35.6261125
        ],
        [
          139.30514139,
          35.626055
        ],
        [
          139.30521056,
          35.62601556
        ],
        [
          139.30537611,
          35.62600417
        ],
        [
          139.30545194,
          35.62599306
        ],
        [
          139.30554861,
          35.62595361
        ],
        [
          139.30579,
          35.62579583
        ],
        [
          139.30598972,
          35.62569444
        ],
        [
          139.30603806,
          35.62569444
        ],
        [
          139.30609306,
          35.62571139
        ],
        [
          139.30640361,
          35.62589722
        ],
        [
          139.30754861,
          35.62673111
        ],
        [
          139.30786583,
          35.626945
        ],
        [
          139.30800389,
          35.62700139
        ],
        [
          139.30820361,
          35.62705778
        ],
        [
          139.30838306,
          35.62714778
        ],
        [
          139.30845889,
          35.62723222
        ],
        [
          139.30853472,
          35.62735056
        ],
        [
          139.30859667,
          35.62751389
        ],
        [
          139.30863806,
          35.62756472
        ],
        [
          139.30867944,
          35.62758139
        ],
        [
          139.30883139,
          35.62758722
        ],
        [
          139.30903972,
          35.62760833
        ],
        [
          139.30905194,
          35.62760972
        ],
        [
          139.30911417,
          35.62763778
        ],
        [
          139.30919,
          35.62771667
        ],
        [
          139.30922444,
          35.62780111
        ],
        [
          139.30925194,
          35.62802667
        ],
        [
          139.30933472,
          35.62819
        ],
        [
          139.3094175,
          35.62830278
        ],
        [
          139.30953472,
          35.62841528
        ],
        [
          139.30954167,
          35.62844917
        ],
        [
          139.30947972,
          35.62855611
        ],
        [
          139.30947972,
          35.62861806
        ],
        [
          139.30949333,
          35.62865194
        ],
        [
          139.30960389,
          35.62878167
        ],
        [
          139.30966583,
          35.62883778
        ],
        [
          139.30970722,
          35.62889972
        ],
        [
          139.30970028,
          35.62889417
        ],
        [
          139.30971417,
          35.62893917
        ],
        [
          139.30972806,
          35.6291025
        ],
        [
          139.30972111,
          35.62911361
        ],
        [
          139.309735,
          35.62913056
        ],
        [
          139.30974861,
          35.62919806
        ],
        [
          139.30980389,
          35.62924889
        ],
        [
          139.30996917,
          35.62928278
        ],
        [
          139.31022444,
          35.62931083
        ],
        [
          139.31043806,
          35.62935028
        ],
        [
          139.31045889,
          35.62934472
        ],
        [
          139.31053389,
          35.62937
        ],
        [
          139.31069361,
          35.62940639
        ],
        [
          139.31085194,
          35.62942361
        ],
        [
          139.31086583,
          35.62943472
        ],
        [
          139.31120389,
          35.62946861
        ],
        [
          139.31134861,
          35.6295025
        ],
        [
          139.31155556,
          35.6295925
        ],
        [
          139.31163139,
          35.62964333
        ],
        [
          139.31175556,
          35.62971083
        ],
        [
          139.31188667,
          35.62971639
        ],
        [
          139.31203833,
          35.62966028
        ],
        [
          139.312135,
          35.62966028
        ],
        [
          139.31217639,
          35.62968278
        ],
        [
          139.31239722,
          35.62993611
        ],
        [
          139.31244528,
          35.62996444
        ],
        [
          139.31286583,
          35.63008278
        ],
        [
          139.31299694,
          35.63007139
        ],
        [
          139.31303694,
          35.63006528
        ],
        [
          139.31307583,
          35.63005667
        ],
        [
          139.31311333,
          35.63005417
        ],
        [
          139.31315389,
          35.6300425
        ],
        [
          139.31320528,
          35.63006194
        ],
        [
          139.31326778,
          35.63010889
        ],
        [
          139.31330056,
          35.63012222
        ],
        [
          139.31330056,
          35.63014472
        ],
        [
          139.31334861,
          35.63019528
        ],
        [
          139.31336944,
          35.63038139
        ],
        [
          139.31340389,
          35.63046028
        ],
        [
          139.31346611,
          35.63049389
        ],
        [
          139.31372111,
          35.63051083
        ],
        [
          139.31381778,
          35.63053333
        ],
        [
          139.31395583,
          35.63060111
        ],
        [
          139.31401778,
          35.63060667
        ],
        [
          139.31414889,
          35.63052778
        ],
        [
          139.31425917,
          35.63048278
        ]
      ]
    ]
  },
  "links": [
    {
      "rel": "root",
      "href": "../../../catalog.json",
      "type": "application/json"
    },
    {
      "rel": "collection",
      "href": "../collection.json",
      "type": "application/json"
    },
    {
      "rel": "parent",
      "href": "../collection.json",
      "type": "application/json"
    }
  ],
  "assets": {},
  "bbox": [
    139.30126556,
    35.62359917,
    139.31425917,
    35.63060667
  ],
  "stac_extensions": [],
  "collection": "8303050000-\u540d\u79f0\u4e0d\u660e"
}