{
  "type": "Feature",
  "stac_version": "1.0.0",
  "id": "130000-1300000000-\u5b89\u5ddd-gb03_1301457-gb03_1301459",
  "properties": {
    "datetime": "2023-03-09T06:08:01.155220Z"
  },
  "geometry": {
    "type": "MultiLineString",
    "coordinates": [
      [
        [
          139.82571417,
          33.06712639
        ],
        [
          139.82560556,
          33.06712639
        ],
        [
          139.82539444,
          33.06722861
        ],
        [
          139.82517139,
          33.06734306
        ],
        [
          139.82496028,
          33.06734917
        ],
        [
          139.82468861,
          33.06730667
        ],
        [
          139.82451833,
          33.06728417
        ],
        [
          139.8242175,
          33.06721083
        ],
        [
          139.82399028,
          33.06712056
        ],
        [
          139.8237225,
          33.06698528
        ],
        [
          139.82364889,
          33.06695722
        ],
        [
          139.82358472,
          33.06693917
        ],
        [
          139.82336806,
          33.06695722
        ],
        [
          139.82328972,
          33.06696139
        ],
        [
          139.82316056,
          33.06695722
        ],
        [
          139.8230025,
          33.06693861
        ],
        [
          139.82275917,
          33.06692333
        ],
        [
          139.82268556,
          33.06690639
        ],
        [
          139.82258528,
          33.06690083
        ],
        [
          139.82213694,
          33.0669175
        ],
        [
          139.8217425,
          33.06692306
        ],
        [
          139.82167556,
          33.06691167
        ],
        [
          139.821515,
          33.06685556
        ],
        [
          139.82138139,
          33.06678778
        ],
        [
          139.82120722,
          33.06664694
        ],
        [
          139.82116722,
          33.06660167
        ],
        [
          139.82097972,
          33.06646639
        ],
        [
          139.82061194,
          33.06626361
        ],
        [
          139.8203375,
          33.06619583
        ],
        [
          139.82021722,
          33.06617889
        ],
        [
          139.82017694,
          33.06618472
        ],
        [
          139.81999639,
          33.06618472
        ],
        [
          139.81986917,
          33.06618472
        ],
        [
          139.81975556,
          33.06624111
        ],
        [
          139.81964167,
          33.06632556
        ],
        [
          139.81947444,
          33.06643833
        ],
        [
          139.81941444,
          33.06644389
        ],
        [
          139.81916667,
          33.06640444
        ],
        [
          139.81903972,
          33.06633667
        ],
        [
          139.81889917,
          33.06628056
        ],
        [
          139.81885917,
          33.06624667
        ],
        [
          139.81873222,
          33.06617889
        ],
        [
          139.81847806,
          33.06589139
        ],
        [
          139.81832417,
          33.06568278
        ],
        [
          139.81826389,
          33.06563222
        ],
        [
          139.81819694,
          33.06559278
        ],
        [
          139.81802972,
          33.06546306
        ],
        [
          139.8179025,
          33.06538972
        ],
        [
          139.81768861,
          33.06534472
        ],
        [
          139.81754139,
          33.06529389
        ],
        [
          139.81745444,
          33.0652375
        ],
        [
          139.8174075,
          33.06515306
        ],
        [
          139.81740083,
          33.06507417
        ],
        [
          139.81741417,
          33.06502333
        ],
        [
          139.81742083,
          33.06494444
        ],
        [
          139.81745444,
          33.064725
        ],
        [
          139.81745444,
          33.06411056
        ],
        [
          139.81740083,
          33.0639075
        ],
        [
          139.81738778,
          33.06369333
        ],
        [
          139.81734083,
          33.06362
        ],
        [
          139.8172875,
          33.06358056
        ],
        [
          139.81718028,
          33.06356917
        ],
        [
          139.81712694,
          33.06355222
        ],
        [
          139.81706361,
          33.06353417
        ],
        [
          139.81701139,
          33.06353139
        ],
        [
          139.81697306,
          33.06352417
        ],
        [
          139.8168125,
          33.06347917
        ],
        [
          139.81666417,
          33.06343361
        ],
        [
          139.81662139,
          33.06342056
        ],
        [
          139.816515,
          33.06339083
        ]
      ]
    ]
  },
  "links": [
    {
      "rel": "root",
      "href": "../../../catalog.json",
      "type": "application/json"
    },
    {
      "rel": "collection",
      "href": "../collection.json",
      "type": "application/json"
    },
    {
      "rel": "parent",
      "href": "../collection.json",
      "type": "application/json"
    }
  ],
  "assets": {},
  "bbox": [
    139.816515,
    33.06339083,
    139.82571417,
    33.06734917
  ],
  "stac_extensions": [],
  "collection": "1300000000-\u5b89\u5ddd"
}